setup.py
vserver.py
vserver.egg-info/PKG-INFO
vserver.egg-info/SOURCES.txt
vserver.egg-info/dependency_links.txt
vserver.egg-info/top_level.txt