Metadata-Version: 1.1
Name: vserver
Version: 0.6
Summary: Python interface to Linux-VServer for managing hosting systems.
Home-page: http://www.profv.de/python-vserver/
Author: Volker Grabsch
Author-email: vog@notjusthosting.com
License: UNKNOWN
Platform: UNKNOWN
Classifier: Development Status :: 5 - Production/Stable
Classifier: Environment :: Console
Classifier: Intended Audience :: Developers
Classifier: Intended Audience :: System Administrators
Classifier: License :: OSI Approved :: MIT License
Classifier: Operating System :: POSIX :: Linux
Classifier: Programming Language :: Python
Classifier: Topic :: Software Development :: Libraries :: Python Modules
Classifier: Topic :: System :: Installation/Setup
Classifier: Topic :: System :: Systems Administration
Classifier: Topic :: Utilities
